Dockerfile
LICENSE.txt
MANIFEST.in
README.md
requirements.txt
setup.py
maven_proxy/__init__.py
maven_proxy/app.py
maven_proxy/config.py
maven_proxy/db.py
maven_proxy/help.py
maven_proxy/job.py
maven_proxy/proxy.py
maven_proxy/task.py
maven_proxy/utils.py
maven_proxy.egg-info/PKG-INFO
maven_proxy.egg-info/SOURCES.txt
maven_proxy.egg-info/dependency_links.txt
maven_proxy.egg-info/entry_points.txt
maven_proxy.egg-info/requires.txt
maven_proxy.egg-info/top_level.txt
maven_proxy/static/favicon.ico
maven_proxy/static/robots.txt
maven_proxy/static/css/all.min.css
maven_proxy/static/webfonts/fa-regular-400.ttf
maven_proxy/static/webfonts/fa-regular-400.woff2
maven_proxy/static/webfonts/fa-solid-900.ttf
maven_proxy/static/webfonts/fa-solid-900.woff2
maven_proxy/templates/directory_listing.html
maven_proxy/templates/login.html