Metadata-Version: 2.4
Name: maven-proxy
Version: 1.2.90
Summary: Maven Repository Proxy with caching and authentication
Home-page: https://github.com/qicongsheng/maven-proxy
Author: qicongsheng
Author-email: qicongsheng@outlook.com
License-File: LICENSE.txt
Requires-Dist: flask
Requires-Dist: requests
Requires-Dist: flask_httpauth
Dynamic: author
Dynamic: author-email
Dynamic: home-page
Dynamic: license-file
Dynamic: requires-dist
Dynamic: summary
